tinybird/context.py
tinybird/datatypes.py
tinybird/feedback_manager.py
tinybird/git_settings.py
tinybird/prompts.py
tinybird/service_datasources.py
tinybird/sql.py
tinybird/sql_template.py
tinybird/sql_template_fmt.py
tinybird/sql_toolset.py
tinybird/syncasync.py
tinybird/tornado_template.py
tinybird/ch_utils/constants.py
tinybird/ch_utils/engine.py
tinybird/datafile/common.py
tinybird/datafile/exceptions.py
tinybird/datafile/parse_connection.py
tinybird/datafile/parse_datasource.py
tinybird/datafile/parse_pipe.py
tinybird/tb/__cli__.py
tinybird/tb/check_pypi.py
tinybird/tb/cli.py
tinybird/tb/client.py
tinybird/tb/config.py
tinybird/tb/modules/branch.py
tinybird/tb/modules/build.py
tinybird/tb/modules/build_common.py
tinybird/tb/modules/cicd.py
tinybird/tb/modules/cli.py
tinybird/tb/modules/common.py
tinybird/tb/modules/config.py
tinybird/tb/modules/connection.py
tinybird/tb/modules/connection_kafka.py
tinybird/tb/modules/connection_s3.py
tinybird/tb/modules/copy.py
tinybird/tb/modules/create.py
tinybird/tb/modules/datasource.py
tinybird/tb/modules/deployment.py
tinybird/tb/modules/deployment_common.py
tinybird/tb/modules/deprecations.py
tinybird/tb/modules/dev_server.py
tinybird/tb/modules/endpoint.py
tinybird/tb/modules/exceptions.py
tinybird/tb/modules/feedback_manager.py
tinybird/tb/modules/fmt.py
tinybird/tb/modules/info.py
tinybird/tb/modules/infra.py
tinybird/tb/modules/job.py
tinybird/tb/modules/job_common.py
tinybird/tb/modules/llm.py
tinybird/tb/modules/llm_utils.py
tinybird/tb/modules/local.py
tinybird/tb/modules/local_common.py
tinybird/tb/modules/local_logs.py
tinybird/tb/modules/login.py
tinybird/tb/modules/login_common.py
tinybird/tb/modules/logout.py
tinybird/tb/modules/materialization.py
tinybird/tb/modules/mock.py
tinybird/tb/modules/mock_common.py
tinybird/tb/modules/open.py
tinybird/tb/modules/pipe.py
tinybird/tb/modules/project.py
tinybird/tb/modules/project_commands.py
tinybird/tb/modules/regions.py
tinybird/tb/modules/secret.py
tinybird-3.1.0.dist-info/METADATA
tinybird-3.1.0.dist-info/WHEEL
tinybird-3.1.0.dist-info/entry_points.txt
tinybird-3.1.0.dist-info/top_level.txt
tinybird-3.1.0.dist-info/RECORD
